odoo/addons/l10n_eu_adr_report/README.rst
odoo/addons/l10n_eu_adr_report/__init__.py
odoo/addons/l10n_eu_adr_report/__manifest__.py
odoo/addons/l10n_eu_adr_report/data/product_picking_demo.xml
odoo/addons/l10n_eu_adr_report/i18n/l10n_eu_adr_report.pot
odoo/addons/l10n_eu_adr_report/i18n/nl.po
odoo/addons/l10n_eu_adr_report/readme/AUTHORS.rst
odoo/addons/l10n_eu_adr_report/readme/DESCRIPTION.rst
odoo/addons/l10n_eu_adr_report/readme/ROADMAP.rst
odoo/addons/l10n_eu_adr_report/report/__init__.py
odoo/addons/l10n_eu_adr_report/report/dangerous_delivery_report.py
odoo/addons/l10n_eu_adr_report/report/dangerous_good_delivery_report.xml
odoo/addons/l10n_eu_adr_report/static/description/icon.png
odoo/addons/l10n_eu_adr_report/static/description/index.html
odoo/addons/l10n_eu_adr_report/static/src/scss/adr_report.scss
odoo/addons/l10n_eu_adr_report/views/assets.xml
odoo13_addon_l10n_eu_adr_report-13.0.1.0.2.dist-info/METADATA
odoo13_addon_l10n_eu_adr_report-13.0.1.0.2.dist-info/WHEEL
odoo13_addon_l10n_eu_adr_report-13.0.1.0.2.dist-info/top_level.txt
odoo13_addon_l10n_eu_adr_report-13.0.1.0.2.dist-info/RECORD
