Metadata-Version: 2.1
Name: odoo13-addon-l10n-eu-adr-report
Version: 13.0.1.0.2
Summary: Print Delivery report to ADR standart
Home-page: https://github.com/OCA/community-data-files
Author: Camptocamp, Odoo Community Association (OCA)
Author-email: support@odoo-community.org
License: AGPL-3
Platform: UNKNOWN
Classifier: Programming Language :: Python
Classifier: Framework :: Odoo
Classifier: Framework :: Odoo :: 13.0
Classifier: License :: OSI Approved :: GNU Affero General Public License v3
Classifier: Development Status :: 3 - Alpha
Requires-Python: >=3.5
Requires-Dist: odoo13-addon-l10n-eu-product-adr
Requires-Dist: odoo (<13.1dev,>=13.0a)
